Metadata-Version: 1.0
Name: deeplearnt
Version: 0.0.3
Summary: clinical trial information retriver
Home-page: https://github.com/pergrand/deeplearntool
Author: lowe.li
Author-email: alilzg@aliyun.com
License: MIT
Platform: UNKNOWN
